captif_data_structures/__init__.py
captif_data_structures/helpers.py
captif_data_structures/readers.py
captif_data_structures/structure/__init__.py
captif_data_structures/structure/base.py
captif_data_structures/structure/deflection_beam.py
captif_data_structures/structure/demo.py
captif_data_structures/structure/lap_count.py
captif_data_structures/structure/texture.py
captif_data_structures-0.12.dist-info/LICENSE
captif_data_structures-0.12.dist-info/WHEEL
captif_data_structures-0.12.dist-info/METADATA
captif_data_structures-0.12.dist-info/RECORD
