Metadata-Version: 2.1
Name: captif-data-structures
Version: 0.12
Summary: 
Home-page: https://github.com/captif-nz/captif-data-structures
License: MIT
Keywords: CAPTIF
Author: John Bull
Requires-Python: >=3.8,<4.0
Classifier: License :: OSI Approved :: MIT License
Classifier: Programming Language :: Python :: 3
Classifier: Programming Language :: Python :: 3.10
Classifier: Programming Language :: Python :: 3.8
Classifier: Programming Language :: Python :: 3.9
Requires-Dist: pandas (>=1.3.3,<2.0.0)
Requires-Dist: parse (>=1.19.0,<2.0.0)
Requires-Dist: psutil (>=5.8.0,<6.0.0)
Requires-Dist: pydantic (>=1.8.2,<2.0.0)
Requires-Dist: unsync (>=1.4.0,<2.0.0)
